layoutlens/__init__.py
layoutlens/api/__init__.py
layoutlens/api/core.py
layoutlens/api/test_suite.py
layoutlens/cache.py
layoutlens/capture.py
layoutlens/cli.py
layoutlens/config.py
layoutlens/exceptions.py
layoutlens/logger.py
layoutlens/prompts/__init__.py
layoutlens/prompts/base.py
layoutlens/prompts/context.py
layoutlens/prompts/experts.py
layoutlens/prompts/utils.py
layoutlens/types.py
layoutlens-1.5.0.dist-info/WHEEL
layoutlens-1.5.0.dist-info/entry_points.txt
layoutlens-1.5.0.dist-info/METADATA
layoutlens-1.5.0.dist-info/RECORD
