Metadata-Version: 2.4
Name: layoutlens
Version: 1.5.0
Summary: AI-powered UI testing framework with natural language visual validation
Keywords: ui testing,visual regression,ai,computer vision,web testing,layout testing
Author: Gaurav Sood
Author-email: Gaurav Sood <contact@gsood.com>
License-Expression: MIT
Classifier: Development Status :: 5 - Production/Stable
Classifier: Intended Audience :: Developers
Classifier: License :: OSI Approved :: MIT License
Classifier: Programming Language :: Python :: 3
Classifier: Programming Language :: Python :: 3.11
Classifier: Programming Language :: Python :: 3.12
Classifier: Programming Language :: Python :: 3.13
Classifier: Topic :: Software Development :: Testing
Classifier: Topic :: Internet :: WWW/HTTP :: Dynamic Content
Classifier: Topic :: Multimedia :: Graphics :: Capture :: Screen Capture
Classifier: Operating System :: OS Independent
Requires-Dist: openai>=1.0.0
Requires-Dist: playwright>=1.40.0
Requires-Dist: beautifulsoup4>=4.12.0
Requires-Dist: pyyaml>=6.0
Requires-Dist: pillow>=10.0.0
Requires-Dist: litellm>=1.80.10
Requires-Dist: rich>=13.0.0
Requires-Dist: pydantic>=2.0.0
Maintainer: Gaurav Sood
Maintainer-email: Gaurav Sood <contact@gsood.com>
Requires-Python: >=3.11
Project-URL: Bug Reports, https://github.com/gojiplus/layoutlens/issues
Project-URL: Changelog, https://github.com/gojiplus/layoutlens/blob/main/CHANGELOG.md
Project-URL: Documentation, https://gojiplus.github.io/layoutlens/
Project-URL: Homepage, https://github.com/gojiplus/layoutlens
Project-URL: Source, https://github.com/gojiplus/layoutlens
